yunomi/__init__.py
yunomi/compat.py
yunomi/core/__init__.py
yunomi/core/counter.py
yunomi/core/histogram.py
yunomi/core/meter.py
yunomi/core/metrics_registry.py
yunomi/core/timer.py
yunomi/stats/__init__.py
yunomi/stats/ewma.py
yunomi/stats/exp_decay_sample.py
yunomi/stats/snapshot.py
yunomi/stats/uniform_sample.py
yunomi/tests/__init__.py
yunomi/tests/test_counter.py
yunomi/tests/test_EWMA.py
yunomi/tests/test_exp_decay_sample_test.py
yunomi/tests/test_histogram.py
yunomi/tests/test_meter.py
yunomi/tests/test_metrics_registry.py
yunomi/tests/test_snapshot.py
yunomi/tests/test_timer.py
yunomi/tests/test_uniform_sample.py
yunomi/tests/util.py
yunomi-0.3.0.dist-info/DESCRIPTION.rst
yunomi-0.3.0.dist-info/METADATA
yunomi-0.3.0.dist-info/pydist.json
yunomi-0.3.0.dist-info/RECORD
yunomi-0.3.0.dist-info/top_level.txt
yunomi-0.3.0.dist-info/WHEEL
